sleeper_service/__init__.py
sleeper_service/sleeper.pyw
sleeper_service-0.11.0.dist-info/METADATA
sleeper_service-0.11.0.dist-info/WHEEL
sleeper_service-0.11.0.dist-info/licenses/LICENSE
sleeper_service-0.11.0.dist-info/RECORD
