Metadata-Version: 2.4
Name: sleeper_service
Version: 0.11.0
Summary: Windows utility to override power requests blocking sleep/hibernate.
Project-URL: Homepage, https://github.com/BuongiornoTexas/sleeper_service
Project-URL: Bug Tracker, https://github.com/BuongiornoTexas/sleeper_service/issues
Author: BuongiornoTexas
License-File: LICENSE
Classifier: License :: OSI Approved :: MIT License
Classifier: Operating System :: OS Independent
Classifier: Programming Language :: Python :: 3
Requires-Python: >=3.11
Requires-Dist: pydantic-settings
Requires-Dist: pywin32
Requires-Dist: tomli-w
Requires-Dist: tray-manager
